COPYING
MANIFEST.in
setup.cfg
setup.py
django_testscenarios/__init__.py
django_testscenarios/models.py
django_testscenarios/tests.py
django_testscenarios/ubertest.py
django_testscenarios.egg-info/PKG-INFO
django_testscenarios.egg-info/SOURCES.txt
django_testscenarios.egg-info/dependency_links.txt
django_testscenarios.egg-info/requires.txt
django_testscenarios.egg-info/top_level.txt
django_testscenarios.egg-info/zip-safe
django_testscenarios/test_project/__init__.py
django_testscenarios/test_project/__init__.pyc
django_testscenarios/test_project/manage.py
django_testscenarios/test_project/settings.py
django_testscenarios/test_project/settings.pyc
django_testscenarios/test_project/tests.py
django_testscenarios/test_project/tests.pyc