Metadata-Version: 1.1
Name: django-testscenarios
Version: 0.7.3
Summary: Test scenarios for Django
Home-page: https://git.linaro.org/lava/django-testscenarios.git
Author: Linaro Limited
Author-email: lava-team@linaro.org
License: LGPLv3
Keywords: django,testing,scenarios
Platform: UNKNOWN
Classifier: Development Status :: 4 - Beta
Classifier: Environment :: Web Environment
Classifier: Framework :: Django
Classifier: Intended Audience :: Developers
Classifier: License :: OSI Approved :: GNU Library or Lesser General Public License (LGPL)
Classifier: Operating System :: OS Independent
Classifier: Programming Language :: Python :: 2.7
Classifier: Topic :: Software Development :: Testing
